youwol/__init__.py
youwol/app/__init__.py
youwol/app/fastapi_app.py
youwol/app/main.py
youwol/app/main_args.py
youwol/app/shut_down.py
youwol/app/start.py
youwol/app/web_socket.py
youwol/app/wrapper.py
youwol/app/environment/__init__.py
youwol/app/environment/browser_cache_store.py
youwol/app/environment/clients.py
youwol/app/environment/config_from_module.py
youwol/app/environment/errors_handling.py
youwol/app/environment/local_auth.py
youwol/app/environment/native_backends_config.py
youwol/app/environment/online_environments.py
youwol/app/environment/paths.py
youwol/app/environment/proxied_backends.py
youwol/app/environment/proxied_esm_servers.py
youwol/app/environment/python_dynamic_loader.py
youwol/app/environment/youwol_environment.py
youwol/app/environment/youwol_environment_models.py
youwol/app/environment/models/__init__.py
youwol/app/environment/models/defaults.py
youwol/app/environment/models/flow_switches.py
youwol/app/environment/models/model_remote.py
youwol/app/environment/models/models.py
youwol/app/environment/models/models_config.py
youwol/app/environment/models/models_project.py
youwol/app/environment/models/models_token_storage.py
youwol/app/environment/models/predefined_configs/__init__.py
youwol/app/environment/models/predefined_configs/default_config.py
youwol/app/environment/models/tokens_storage/__init__.py
youwol/app/environment/models/tokens_storage/encrypted_file.py
youwol/app/environment/models/tokens_storage/file.py
youwol/app/environment/models/tokens_storage/path_base.py
youwol/app/middlewares/__init__.py
youwol/app/middlewares/browser_middleware.py
youwol/app/middlewares/esm_servers_middleware.py
youwol/app/middlewares/hybridizer_middleware.py
youwol/app/middlewares/local_cloud_hybridizers/__init__.py
youwol/app/middlewares/local_cloud_hybridizers/abstract_local_cloud_dispatch.py
youwol/app/middlewares/local_cloud_hybridizers/common.py
youwol/app/middlewares/local_cloud_hybridizers/custom_backends.py
youwol-0.1.12.dist-info/LICENSE
youwol-0.1.12.dist-info/METADATA
youwol-0.1.12.dist-info/WHEEL
youwol-0.1.12.dist-info/entry_points.txt
youwol-0.1.12.dist-info/top_level.txt
youwol-0.1.12.dist-info/RECORD
