Metadata-Version: 2.1
Name: youwol
Version: 0.1.12
Summary: YouWol as a desktop application
Author-email: "G. Reinisch" <greinisch@youwol.com>, "J. Decharne" <jdecharne@youwol.com>
Classifier: License :: OSI Approved :: MIT License
Classifier: Programming Language :: Python :: 3
Classifier: Programming Language :: Python :: 3.10
Classifier: Programming Language :: Python :: 3.11
Classifier: Programming Language :: Python :: 3.12
Requires-Python: ~=3.8
License-File: LICENSE
Requires-Dist: aiohttp <4.0.0,>=3.8.1
Requires-Dist: aiostream <0.5.0,>=0.4.4
Requires-Dist: appdirs <2.0.0,>=1.4.4
Requires-Dist: Brotli <2.0.0,>=1.0.9
Requires-Dist: build <2.0.0,>=1.1.1
Requires-Dist: colorama <0.5.0,>=0.4.5
Requires-Dist: colorlog
Requires-Dist: cowpy <2.0.0,>=1.1.5
Requires-Dist: deepdiff <8.0.0,>=7.0.1
Requires-Dist: fastapi <0.110.0,>=0.109.1
Requires-Dist: keyring <25.0.0,>=24.2.0
Requires-Dist: minio <8.0.0,>=7.1.9
Requires-Dist: Pillow <11.0.0,>=10.3.0
Requires-Dist: psutil <6.0.0,>=5.9.1
Requires-Dist: pycryptodome <4.0.0,>=3.19.0
Requires-Dist: pydantic <2.0.0
Requires-Dist: pyparsing >=3.1.0
Requires-Dist: python-daemon <4,>=3
Requires-Dist: python-multipart <0.0.10,>=0.0.9
Requires-Dist: pyyaml <7.0,>=6.0
Requires-Dist: pyjwt[crypto] <3.0.0,>=2.4.0
Requires-Dist: redis <5.0.0,>=4.3.4
Requires-Dist: tqdm <5.0.0,>=4.64.1
Requires-Dist: uvicorn <0.25,>=0.24
Requires-Dist: websockets <11,>=10.3
Requires-Dist: semantic-version <3.0.0,>=2.10.0
Requires-Dist: watchdog <3.0.0,>=2.1.9
Requires-Dist: prometheus-client
Requires-Dist: tomlkit <0.13,>=0.12.3
Provides-Extra: dev
Requires-Dist: pip-tools ; extra == 'dev'
Provides-Extra: publish
Requires-Dist: pdoc3 ; extra == 'publish'
Requires-Dist: build ; extra == 'publish'
Requires-Dist: twine ; extra == 'publish'
Provides-Extra: qa
Requires-Dist: asgiref ; extra == 'qa'
Requires-Dist: coverage ; extra == 'qa'
Requires-Dist: pip-audit ; extra == 'qa'
Requires-Dist: pylint ; extra == 'qa'
Requires-Dist: pycodestyle ; extra == 'qa'
Requires-Dist: pydocstyle ; extra == 'qa'
Requires-Dist: isort ; extra == 'qa'
Requires-Dist: black[d] ; extra == 'qa'
Requires-Dist: mypy ; extra == 'qa'
Requires-Dist: scylla-driver ; extra == 'qa'
Requires-Dist: tomlkit ; extra == 'qa'
Requires-Dist: types-Pillow ; extra == 'qa'
Requires-Dist: types-PyYAML ; extra == 'qa'
Requires-Dist: types-appdirs ; extra == 'qa'
Requires-Dist: types-colorama ; extra == 'qa'
Requires-Dist: types-psutil ; extra == 'qa'
Requires-Dist: types-redis ; extra == 'qa'
Requires-Dist: types-setuptools ; extra == 'qa'
Requires-Dist: types-tqdm ; extra == 'qa'
Requires-Dist: types-ujson ; extra == 'qa'
Requires-Dist: yamllint ; extra == 'qa'
